{"response": {"status": {"version": "4.2", "code": 0, "message": "Success"}, "track": {"status": "complete", "song_id": "SOBKSQF146192156BA", "artist": "Michael Jackson", "foreign_ids": ["spotify-AD:track:0it16By6VcfBXis67YMNbT", "spotify-AR:track:0it16By6VcfBXis67YMNbT", "spotify-AT:track:0it16By6VcfBXis67YMNbT", "spotify-AU:track:0it16By6VcfBXis67YMNbT", "spotify-BE:track:0it16By6VcfBXis67YMNbT", "spotify-BG:track:0it16By6VcfBXis67YMNbT", "spotify-BO:track:0it16By6VcfBXis67YMNbT", "spotify-BR:track:0it16By6VcfBXis67YMNbT", "spotify-CA:track:0it16By6VcfBXis67YMNbT", "spotify-CH:track:0it16By6VcfBXis67YMNbT", "spotify-CL:track:0it16By6VcfBXis67YMNbT", "spotify-CO:track:0it16By6VcfBXis67YMNbT", "spotify-CR:track:0it16By6VcfBXis67YMNbT", "spotify-CY:track:0it16By6VcfBXis67YMNbT", "spotify-CZ:track:0it16By6VcfBXis67YMNbT", "spotify-DE:track:0it16By6VcfBXis67YMNbT", "spotify-DK:track:0it16By6VcfBXis67YMNbT", "spotify-DO:track:0it16By6VcfBXis67YMNbT", "spotify-EC:track:0it16By6VcfBXis67YMNbT", "spotify-EE:track:0it16By6VcfBXis67YMNbT", "spotify-ES:track:0it16By6VcfBXis67YMNbT", "spotify-FI:track:0it16By6VcfBXis67YMNbT", "spotify-FR:track:0it16By6VcfBXis67YMNbT", "spotify-GB:track:0it16By6VcfBXis67YMNbT", "spotify-GR:track:0it16By6VcfBXis67YMNbT", "spotify-GT:track:0it16By6VcfBXis67YMNbT", "spotify-HK:track:0it16By6VcfBXis67YMNbT", "spotify-HN:track:0it16By6VcfBXis67YMNbT", "spotify-HR:track:0it16By6VcfBXis67YMNbT", "spotify-HU:track:0it16By6VcfBXis67YMNbT", "spotify-IE:track:0it16By6VcfBXis67YMNbT", "spotify-IS:track:0it16By6VcfBXis67YMNbT", "spotify-IT:track:0it16By6VcfBXis67YMNbT", "spotify-LI:track:0it16By6VcfBXis67YMNbT", "spotify-LT:track:0it16By6VcfBXis67YMNbT", "spotify-LU:track:0it16By6VcfBXis67YMNbT", "spotify-LV:track:0it16By6VcfBXis67YMNbT", "spotify-MC:track:0it16By6VcfBXis67YMNbT", "spotify-MT:track:0it16By6VcfBXis67YMNbT", "spotify-MX:track:0it16By6VcfBXis67YMNbT", "spotify-MY:track:0it16By6VcfBXis67YMNbT", "spotify-NI:track:0it16By6VcfBXis67YMNbT", "spotify-NL:track:0it16By6VcfBXis67YMNbT", "spotify-NO:track:0it16By6VcfBXis67YMNbT", "spotify-NZ:track:0it16By6VcfBXis67YMNbT", "spotify-PA:track:0it16By6VcfBXis67YMNbT", "spotify-PE:track:0it16By6VcfBXis67YMNbT", "spotify-PH:track:0it16By6VcfBXis67YMNbT", "spotify-PL:track:0it16By6VcfBXis67YMNbT", "spotify-PT:track:0it16By6VcfBXis67YMNbT", "spotify-PY:track:0it16By6VcfBXis67YMNbT", "spotify-RO:track:0it16By6VcfBXis67YMNbT", "spotify-SE:track:0it16By6VcfBXis67YMNbT", "spotify-SG:track:0it16By6VcfBXis67YMNbT", "spotify-SI:track:0it16By6VcfBXis67YMNbT", "spotify-SK:track:0it16By6VcfBXis67YMNbT", "spotify-SV:track:0it16By6VcfBXis67YMNbT", "spotify-TR:track:0it16By6VcfBXis67YMNbT", "spotify-TW:track:0it16By6VcfBXis67YMNbT", "spotify-US:track:0it16By6VcfBXis67YMNbT", "spotify-UY:track:0it16By6VcfBXis67YMNbT", "spotify:track:0it16By6VcfBXis67YMNbT"], "title": "I Just Can't Stop Loving You - Remastered Version", "foreign_release_ids": ["spotify-AD:album:7pMVCMwGykuEu9rzTHxLCm", "spotify-AR:album:7pMVCMwGykuEu9rzTHxLCm", "spotify-AT:album:7pMVCMwGykuEu9rzTHxLCm", "spotify-AU:album:7pMVCMwGykuEu9rzTHxLCm", "spotify-BE:album:7pMVCMwGykuEu9rzTHxLCm", "spotify-BG:album:7pMVCMwGykuEu9rzTHxLCm", "spotify-BO:album:7pMVCMwGykuEu9rzTHxLCm", "spotify-BR:album:7pMVCMwGykuEu9rzTHxLCm", "spotify-CA:album:7pMVCMwGykuEu9rzTHxLCm", "spotify-CH:album:7pMVCMwGykuEu9rzTHxLCm", "spotify-CL:album:7pMVCMwGykuEu9rzTHxLCm", "spotify-CO:album:7pMVCMwGykuEu9rzTHxLCm", "spotify-CR:album:7pMVCMwGykuEu9rzTHxLCm", "spotify-CY:album:7pMVCMwGykuEu9rzTHxLCm", "spotify-CZ:album:7pMVCMwGykuEu9rzTHxLCm", "spotify-DE:album:7pMVCMwGykuEu9rzTHxLCm", "spotify-DK:album:7pMVCMwGykuEu9rzTHxLCm", "spotify-DO:album:7pMVCMwGykuEu9rzTHxLCm", "spotify-EC:album:7pMVCMwGykuEu9rzTHxLCm", "spotify-EE:album:7pMVCMwGykuEu9rzTHxLCm", "spotify-ES:album:7pMVCMwGykuEu9rzTHxLCm", "spotify-FI:album:7pMVCMwGykuEu9rzTHxLCm", "spotify-FR:album:7pMVCMwGykuEu9rzTHxLCm", "spotify-GB:album:7pMVCMwGykuEu9rzTHxLCm", "spotify-GR:album:7pMVCMwGykuEu9rzTHxLCm", "spotify-GT:album:7pMVCMwGykuEu9rzTHxLCm", "spotify-HK:album:7pMVCMwGykuEu9rzTHxLCm", "spotify-HN:album:7pMVCMwGykuEu9rzTHxLCm", "spotify-HR:album:7pMVCMwGykuEu9rzTHxLCm", "spotify-HU:album:7pMVCMwGykuEu9rzTHxLCm", "spotify-IE:album:7pMVCMwGykuEu9rzTHxLCm", "spotify-IS:album:7pMVCMwGykuEu9rzTHxLCm", "spotify-IT:album:7pMVCMwGykuEu9rzTHxLCm", "spotify-LI:album:7pMVCMwGykuEu9rzTHxLCm", "spotify-LT:album:7pMVCMwGykuEu9rzTHxLCm", "spotify-LU:album:7pMVCMwGykuEu9rzTHxLCm", "spotify-LV:album:7pMVCMwGykuEu9rzTHxLCm", "spotify-MC:album:7pMVCMwGykuEu9rzTHxLCm", "spotify-MT:album:7pMVCMwGykuEu9rzTHxLCm", "spotify-MX:album:7pMVCMwGykuEu9rzTHxLCm", "spotify-MY:album:7pMVCMwGykuEu9rzTHxLCm", "spotify-NI:album:7pMVCMwGykuEu9rzTHxLCm", "spotify-NL:album:7pMVCMwGykuEu9rzTHxLCm", "spotify-NO:album:7pMVCMwGykuEu9rzTHxLCm", "spotify-NZ:album:7pMVCMwGykuEu9rzTHxLCm", "spotify-PA:album:7pMVCMwGykuEu9rzTHxLCm", "spotify-PE:album:7pMVCMwGykuEu9rzTHxLCm", "spotify-PH:album:7pMVCMwGykuEu9rzTHxLCm", "spotify-PL:album:7pMVCMwGykuEu9rzTHxLCm", "spotify-PT:album:7pMVCMwGykuEu9rzTHxLCm", "spotify-PY:album:7pMVCMwGykuEu9rzTHxLCm", "spotify-RO:album:7pMVCMwGykuEu9rzTHxLCm", "spotify-SE:album:7pMVCMwGykuEu9rzTHxLCm", "spotify-SG:album:7pMVCMwGykuEu9rzTHxLCm", "spotify-SI:album:7pMVCMwGykuEu9rzTHxLCm", "spotify-SK:album:7pMVCMwGykuEu9rzTHxLCm", "spotify-SV:album:7pMVCMwGykuEu9rzTHxLCm", "spotify-TR:album:7pMVCMwGykuEu9rzTHxLCm", "spotify-TW:album:7pMVCMwGykuEu9rzTHxLCm", "spotify-US:album:7pMVCMwGykuEu9rzTHxLCm", "spotify-UY:album:7pMVCMwGykuEu9rzTHxLCm", "spotify:album:7pMVCMwGykuEu9rzTHxLCm"], "foreign_release_id": "spotify:album:7pMVCMwGykuEu9rzTHxLCm", "catalog": "spotify", "release": "Michael Jackson's This Is It", "foreign_id": "spotify:track:0it16By6VcfBXis67YMNbT", "id": "TRHCGAM144D0AE69F7", "audio_summary": {"time_signature": 4, "tempo": 100.163, "energy": 0.5024614228920353, "liveness": 0.04696937877913354, "analysis_url": "http://echonest-analysis.s3.amazonaws.com/TR/-EmRqQmzyvMh4BpiVmBxDQ-X3Uu5d3wTZh8PRq4gIbnhIEsl0SZXCAfFZyOtWw29Hpf0fxlP6ol2XtWAc%3D/3/full.json?AWSAccessKeyId=AKIAJRDFEY23UEVW42BQ&Expires=1456362070&Signature=Qfx6pE38yINJi4MjtUvc9bJyTPk%3D", "speechiness": 0.03659963230276708, "mode": 1, "acousticness": 0.6210110567037385, "danceability": 0.6598504348642515, "key": 5, "duration": 252.2, "loudness": -7.715, "valence": 0.2497375463925318, "instrumentalness": 3.445352014517588e-06}}}}