{"response": {"status": {"version": "4.2", "code": 0, "message": "Success"}, "track": {"status": "complete", "song_id": "SOMJDLR1315CD49A1A", "artist": "Bonobo", "foreign_ids": ["spotify-AD:track:0XiHcuUEf1wmvmX1cOaVR9", "spotify-AR:track:0XiHcuUEf1wmvmX1cOaVR9", "spotify-AT:track:0XiHcuUEf1wmvmX1cOaVR9", "spotify-BE:track:0XiHcuUEf1wmvmX1cOaVR9", "spotify-BG:track:0XiHcuUEf1wmvmX1cOaVR9", "spotify-BO:track:0XiHcuUEf1wmvmX1cOaVR9", "spotify-BR:track:0XiHcuUEf1wmvmX1cOaVR9", "spotify-CA:track:0XiHcuUEf1wmvmX1cOaVR9", "spotify-CH:track:0XiHcuUEf1wmvmX1cOaVR9", "spotify-CL:track:0XiHcuUEf1wmvmX1cOaVR9", "spotify-CO:track:0XiHcuUEf1wmvmX1cOaVR9", "spotify-CR:track:0XiHcuUEf1wmvmX1cOaVR9", "spotify-CY:track:0XiHcuUEf1wmvmX1cOaVR9", "spotify-CZ:track:0XiHcuUEf1wmvmX1cOaVR9", "spotify-DE:track:0XiHcuUEf1wmvmX1cOaVR9", "spotify-DK:track:0XiHcuUEf1wmvmX1cOaVR9", "spotify-DO:track:0XiHcuUEf1wmvmX1cOaVR9", "spotify-EC:track:0XiHcuUEf1wmvmX1cOaVR9", "spotify-EE:track:0XiHcuUEf1wmvmX1cOaVR9", "spotify-ES:track:0XiHcuUEf1wmvmX1cOaVR9", "spotify-FI:track:0XiHcuUEf1wmvmX1cOaVR9", "spotify-FR:track:0XiHcuUEf1wmvmX1cOaVR9", "spotify-GB:track:0XiHcuUEf1wmvmX1cOaVR9", "spotify-GR:track:0XiHcuUEf1wmvmX1cOaVR9", "spotify-GT:track:0XiHcuUEf1wmvmX1cOaVR9", "spotify-HK:track:0XiHcuUEf1wmvmX1cOaVR9", "spotify-HN:track:0XiHcuUEf1wmvmX1cOaVR9", "spotify-HR:track:0XiHcuUEf1wmvmX1cOaVR9", "spotify-HU:track:0XiHcuUEf1wmvmX1cOaVR9", "spotify-IE:track:0XiHcuUEf1wmvmX1cOaVR9", "spotify-IS:track:0XiHcuUEf1wmvmX1cOaVR9", "spotify-IT:track:0XiHcuUEf1wmvmX1cOaVR9", "spotify-LI:track:0XiHcuUEf1wmvmX1cOaVR9", "spotify-LT:track:0XiHcuUEf1wmvmX1cOaVR9", "spotify-LU:track:0XiHcuUEf1wmvmX1cOaVR9", "spotify-LV:track:0XiHcuUEf1wmvmX1cOaVR9", "spotify-MC:track:0XiHcuUEf1wmvmX1cOaVR9", "spotify-MT:track:0XiHcuUEf1wmvmX1cOaVR9", "spotify-MX:track:0XiHcuUEf1wmvmX1cOaVR9", "spotify-MY:track:0XiHcuUEf1wmvmX1cOaVR9", "spotify-NI:track:0XiHcuUEf1wmvmX1cOaVR9", "spotify-NL:track:0XiHcuUEf1wmvmX1cOaVR9", "spotify-NO:track:0XiHcuUEf1wmvmX1cOaVR9", "spotify-PA:track:0XiHcuUEf1wmvmX1cOaVR9", "spotify-PE:track:0XiHcuUEf1wmvmX1cOaVR9", "spotify-PH:track:0XiHcuUEf1wmvmX1cOaVR9", "spotify-PL:track:0XiHcuUEf1wmvmX1cOaVR9", "spotify-PT:track:0XiHcuUEf1wmvmX1cOaVR9", "spotify-PY:track:0XiHcuUEf1wmvmX1cOaVR9", "spotify-RO:track:0XiHcuUEf1wmvmX1cOaVR9", "spotify-SE:track:0XiHcuUEf1wmvmX1cOaVR9", "spotify-SG:track:0XiHcuUEf1wmvmX1cOaVR9", "spotify-SI:track:0XiHcuUEf1wmvmX1cOaVR9", "spotify-SK:track:0XiHcuUEf1wmvmX1cOaVR9", "spotify-SV:track:0XiHcuUEf1wmvmX1cOaVR9", "spotify-TR:track:0XiHcuUEf1wmvmX1cOaVR9", "spotify-TW:track:0XiHcuUEf1wmvmX1cOaVR9", "spotify-US:track:0XiHcuUEf1wmvmX1cOaVR9", "spotify-UY:track:0XiHcuUEf1wmvmX1cOaVR9", "spotify:track:0XiHcuUEf1wmvmX1cOaVR9"], "title": "Eyesdown", "foreign_release_ids": ["spotify-AD:album:5m1RkwKeU7MV0Ni6PH2lPy", "spotify-AR:album:5m1RkwKeU7MV0Ni6PH2lPy", "spotify-AT:album:5m1RkwKeU7MV0Ni6PH2lPy", "spotify-BE:album:5m1RkwKeU7MV0Ni6PH2lPy", "spotify-BG:album:5m1RkwKeU7MV0Ni6PH2lPy", "spotify-BO:album:5m1RkwKeU7MV0Ni6PH2lPy", "spotify-BR:album:5m1RkwKeU7MV0Ni6PH2lPy", "spotify-CA:album:5m1RkwKeU7MV0Ni6PH2lPy", "spotify-CH:album:5m1RkwKeU7MV0Ni6PH2lPy", "spotify-CL:album:5m1RkwKeU7MV0Ni6PH2lPy", "spotify-CO:album:5m1RkwKeU7MV0Ni6PH2lPy", "spotify-CR:album:5m1RkwKeU7MV0Ni6PH2lPy", "spotify-CY:album:5m1RkwKeU7MV0Ni6PH2lPy", "spotify-CZ:album:5m1RkwKeU7MV0Ni6PH2lPy", "spotify-DE:album:5m1RkwKeU7MV0Ni6PH2lPy", "spotify-DK:album:5m1RkwKeU7MV0Ni6PH2lPy", "spotify-DO:album:5m1RkwKeU7MV0Ni6PH2lPy", "spotify-EC:album:5m1RkwKeU7MV0Ni6PH2lPy", "spotify-EE:album:5m1RkwKeU7MV0Ni6PH2lPy", "spotify-ES:album:5m1RkwKeU7MV0Ni6PH2lPy", "spotify-FI:album:5m1RkwKeU7MV0Ni6PH2lPy", "spotify-FR:album:5m1RkwKeU7MV0Ni6PH2lPy", "spotify-GB:album:5m1RkwKeU7MV0Ni6PH2lPy", "spotify-GR:album:5m1RkwKeU7MV0Ni6PH2lPy", "spotify-GT:album:5m1RkwKeU7MV0Ni6PH2lPy", "spotify-HK:album:5m1RkwKeU7MV0Ni6PH2lPy", "spotify-HN:album:5m1RkwKeU7MV0Ni6PH2lPy", "spotify-HR:album:5m1RkwKeU7MV0Ni6PH2lPy", "spotify-HU:album:5m1RkwKeU7MV0Ni6PH2lPy", "spotify-IE:album:5m1RkwKeU7MV0Ni6PH2lPy", "spotify-IS:album:5m1RkwKeU7MV0Ni6PH2lPy", "spotify-IT:album:5m1RkwKeU7MV0Ni6PH2lPy", "spotify-LI:album:5m1RkwKeU7MV0Ni6PH2lPy", "spotify-LT:album:5m1RkwKeU7MV0Ni6PH2lPy", "spotify-LU:album:5m1RkwKeU7MV0Ni6PH2lPy", "spotify-LV:album:5m1RkwKeU7MV0Ni6PH2lPy", "spotify-MC:album:5m1RkwKeU7MV0Ni6PH2lPy", "spotify-MT:album:5m1RkwKeU7MV0Ni6PH2lPy", "spotify-MX:album:5m1RkwKeU7MV0Ni6PH2lPy", "spotify-MY:album:5m1RkwKeU7MV0Ni6PH2lPy", "spotify-NI:album:5m1RkwKeU7MV0Ni6PH2lPy", "spotify-NL:album:5m1RkwKeU7MV0Ni6PH2lPy", "spotify-NO:album:5m1RkwKeU7MV0Ni6PH2lPy", "spotify-PA:album:5m1RkwKeU7MV0Ni6PH2lPy", "spotify-PE:album:5m1RkwKeU7MV0Ni6PH2lPy", "spotify-PH:album:5m1RkwKeU7MV0Ni6PH2lPy", "spotify-PL:album:5m1RkwKeU7MV0Ni6PH2lPy", "spotify-PT:album:5m1RkwKeU7MV0Ni6PH2lPy", "spotify-PY:album:5m1RkwKeU7MV0Ni6PH2lPy", "spotify-RO:album:5m1RkwKeU7MV0Ni6PH2lPy", "spotify-SE:album:5m1RkwKeU7MV0Ni6PH2lPy", "spotify-SG:album:5m1RkwKeU7MV0Ni6PH2lPy", "spotify-SI:album:5m1RkwKeU7MV0Ni6PH2lPy", "spotify-SK:album:5m1RkwKeU7MV0Ni6PH2lPy", "spotify-SV:album:5m1RkwKeU7MV0Ni6PH2lPy", "spotify-TR:album:5m1RkwKeU7MV0Ni6PH2lPy", "spotify-TW:album:5m1RkwKeU7MV0Ni6PH2lPy", "spotify-US:album:5m1RkwKeU7MV0Ni6PH2lPy", "spotify-UY:album:5m1RkwKeU7MV0Ni6PH2lPy", "spotify:album:5m1RkwKeU7MV0Ni6PH2lPy"], "foreign_release_id": "spotify:album:5m1RkwKeU7MV0Ni6PH2lPy", "catalog": "spotify", "release": "Black Sands", "foreign_id": "spotify:track:0XiHcuUEf1wmvmX1cOaVR9", "id": "TRSQUCH144D0A6D90C", "audio_summary": {"time_signature": 3, "tempo": 129.976, "energy": 0.4552647510692434, "liveness": 0.10952358224514253, "analysis_url": "http://echonest-analysis.s3.amazonaws.com/TR/MPeNZwo6q7bJ2E8qfAZ2M2DUm7BYtP6smKplC4EZwJz2KyZCRdP1k5-Qd7Sq9Z5rM0aD5I0lTgqdQ773E%3D/3/full.json?AWSAccessKeyId=AKIAJRDFEY23UEVW42BQ&Expires=1456355787&Signature=qbkt7LBNULgvu2UFKaZvhMfNkTk%3D", "speechiness": 0.12008030291310495, "mode": 0, "acousticness": 0.0442125056630136, "danceability": 0.7576860380678425, "key": 4, "duration": 326.24, "loudness": -9.199, "valence": 0.18031239506291805, "instrumentalness": 0.49315474138343823}}}}