{"response": {"status": {"version": "4.2", "code": 0, "message": "Success"}, "track": {"status": "complete", "song_id": "SORIQFM1376E9F8CDF", "artist": "Depeche Mode", "foreign_ids": ["spotify-CA:track:12Gbz1qkaCAFPGlYVVw6xZ", "spotify-MX:track:12Gbz1qkaCAFPGlYVVw6xZ", "spotify-US:track:12Gbz1qkaCAFPGlYVVw6xZ", "spotify:track:12Gbz1qkaCAFPGlYVVw6xZ"], "title": "Enjoy The Silence - Remastered Version Original", "foreign_release_ids": ["spotify-CA:album:3PIszA6UT9iI99izK60AdV", "spotify-MX:album:3PIszA6UT9iI99izK60AdV", "spotify-US:album:3PIszA6UT9iI99izK60AdV", "spotify:album:3PIszA6UT9iI99izK60AdV"], "foreign_release_id": "spotify:album:3PIszA6UT9iI99izK60AdV", "catalog": "spotify", "release": "The Best Of Depeche Mode Volume 1", "foreign_id": "spotify:track:12Gbz1qkaCAFPGlYVVw6xZ", "id": "TRDWPZM144D0BB1D70", "audio_summary": {"time_signature": 4, "tempo": 112.923, "energy": 0.7702294819133952, "liveness": 0.11414219743802224, "analysis_url": "http://echonest-analysis.s3.amazonaws.com/TR/5pGzxwPDMGtoolZCQ2iZbtNQaa13pFNzQE2-i_cSwcpKlVA5nfc4LhIxkMUBSvW7yGsVvW3Ge8ox02TQ0%3D/3/full.json?AWSAccessKeyId=AKIAJRDFEY23UEVW42BQ&Expires=1456273985&Signature=rZ5Bc1oxW%2BSERAMq6WBSc0/sHGI%3D", "speechiness": 0.027403536713944687, "mode": 0, "acousticness": 0.08099760247889612, "danceability": 0.6510816287379262, "key": 0, "duration": 253.58667, "loudness": -8.08, "valence": 0.7382086624635907, "instrumentalness": 6.543678742716494e-05}}}}