{"response": {"status": {"version": "4.2", "code": 0, "message": "Success"}, "track": {"status": "complete", "song_id": "SOYPJUM12A8C140659", "artist": "Jónsi & Alex", "foreign_ids": ["spotify-CA:track:3BO3R8SLyb9cfSCgk1kXUl", "spotify-US:track:3BO3R8SLyb9cfSCgk1kXUl", "spotify:track:3BO3R8SLyb9cfSCgk1kXUl"], "title": "Happiness", "foreign_release_ids": ["spotify-CA:album:7geaPgu6PxeEyhBOa20ajZ", "spotify-US:album:7geaPgu6PxeEyhBOa20ajZ", "spotify:album:7geaPgu6PxeEyhBOa20ajZ"], "foreign_release_id": "spotify:album:7geaPgu6PxeEyhBOa20ajZ", "catalog": "spotify", "release": "Riceboy Sleeps", "foreign_id": "spotify:track:3BO3R8SLyb9cfSCgk1kXUl", "id": "TRHHDUF144D117C5E0", "audio_summary": {"time_signature": 1, "tempo": 138.457, "energy": 0.24676228530191993, "liveness": 0.09030324707371452, "analysis_url": "http://echonest-analysis.s3.amazonaws.com/TR/U7U7mAiV2xndatajd3UhANNvqGrfzeh2DnNtzVnh7-noyt2FzAMmrHJa9xCt70arS4nDlWR9m18kOasQE%3D/3/full.json?AWSAccessKeyId=AKIAJRDFEY23UEVW42BQ&Expires=1456358038&Signature=0CWEMUtcyFelgxt9lKpjUbiLAKI%3D", "speechiness": 0.03870342072292443, "mode": 1, "acousticness": 0.8673128719596094, "danceability": 0.1466851866545539, "key": 7, "duration": 560.65333, "loudness": -16.216, "valence": 0.03832165018361031, "instrumentalness": 0.9711060311826303}}}}