{"response": {"status": {"version": "4.2", "code": 0, "message": "Success"}, "track": {"status": "complete", "song_id": "SOMXIBD1312FE01D4A", "artist": "Rodrigo y Gabriela", "foreign_ids": ["spotify-MX:track:3Cb3CCmo58SF9BJGZsjMut", "spotify-US:track:3Cb3CCmo58SF9BJGZsjMut", "spotify:track:3Cb3CCmo58SF9BJGZsjMut"], "title": "Chac Mool", "foreign_release_ids": ["spotify-MX:album:1wt3Ns19lsRSHh6ZwED1tx", "spotify-US:album:1wt3Ns19lsRSHh6ZwED1tx", "spotify:album:1wt3Ns19lsRSHh6ZwED1tx"], "foreign_release_id": "spotify:album:1wt3Ns19lsRSHh6ZwED1tx", "catalog": "spotify", "release": "11:11", "foreign_id": "spotify:track:3Cb3CCmo58SF9BJGZsjMut", "id": "TRVOCVE144D118A531", "audio_summary": {"time_signature": 4, "tempo": 75.018, "energy": 0.1563370425486414, "liveness": 0.12245030352583149, "analysis_url": "http://echonest-analysis.s3.amazonaws.com/TR/6su_HwLmSXcZ4RVjCc79JwSV-43PCN1JhPgcPfoQzLZ8LbJF5LOcFyn7dvN8jUGFi-lW2laNUty2i_HqE%3D/3/full.json?AWSAccessKeyId=AKIAJRDFEY23UEVW42BQ&Expires=1456378747&Signature=Q31t/crTt%2Bt7I4s4T4goEg4BPoM%3D", "speechiness": 0.06336171634140852, "mode": 1, "acousticness": 0.9733090797788463, "danceability": 0.675252959730871, "key": 2, "duration": 111.33333, "loudness": -18.637, "valence": 0.19095328452127674, "instrumentalness": 0.9536557226547531}}}}