{"response": {"status": {"version": "4.2", "code": 0, "message": "Success"}, "track": {"status": "complete", "song_id": "SOSVEFX148B95FBF26", "artist": "Dillon Francis", "foreign_ids": ["spotify-AD:track:3KHwhq1ZsfBwRYtacrXqVP", "spotify-AR:track:3KHwhq1ZsfBwRYtacrXqVP", "spotify-AT:track:3KHwhq1ZsfBwRYtacrXqVP", "spotify-AU:track:3KHwhq1ZsfBwRYtacrXqVP", "spotify-BE:track:3KHwhq1ZsfBwRYtacrXqVP", "spotify-BG:track:3KHwhq1ZsfBwRYtacrXqVP", "spotify-BO:track:3KHwhq1ZsfBwRYtacrXqVP", "spotify-BR:track:3KHwhq1ZsfBwRYtacrXqVP", "spotify-CA:track:3KHwhq1ZsfBwRYtacrXqVP", "spotify-CH:track:3KHwhq1ZsfBwRYtacrXqVP", "spotify-CL:track:3KHwhq1ZsfBwRYtacrXqVP", "spotify-CO:track:3KHwhq1ZsfBwRYtacrXqVP", "spotify-CR:track:3KHwhq1ZsfBwRYtacrXqVP", "spotify-CY:track:3KHwhq1ZsfBwRYtacrXqVP", "spotify-CZ:track:3KHwhq1ZsfBwRYtacrXqVP", "spotify-DE:track:3KHwhq1ZsfBwRYtacrXqVP", "spotify-DK:track:3KHwhq1ZsfBwRYtacrXqVP", "spotify-DO:track:3KHwhq1ZsfBwRYtacrXqVP", "spotify-EC:track:3KHwhq1ZsfBwRYtacrXqVP", "spotify-EE:track:3KHwhq1ZsfBwRYtacrXqVP", "spotify-ES:track:3KHwhq1ZsfBwRYtacrXqVP", "spotify-FI:track:3KHwhq1ZsfBwRYtacrXqVP", "spotify-FR:track:3KHwhq1ZsfBwRYtacrXqVP", "spotify-GB:track:3KHwhq1ZsfBwRYtacrXqVP", "spotify-GR:track:3KHwhq1ZsfBwRYtacrXqVP", "spotify-GT:track:3KHwhq1ZsfBwRYtacrXqVP", "spotify-HK:track:3KHwhq1ZsfBwRYtacrXqVP", "spotify-HN:track:3KHwhq1ZsfBwRYtacrXqVP", "spotify-HR:track:3KHwhq1ZsfBwRYtacrXqVP", "spotify-HU:track:3KHwhq1ZsfBwRYtacrXqVP", "spotify-IE:track:3KHwhq1ZsfBwRYtacrXqVP", "spotify-IS:track:3KHwhq1ZsfBwRYtacrXqVP", "spotify-IT:track:3KHwhq1ZsfBwRYtacrXqVP", "spotify-LI:track:3KHwhq1ZsfBwRYtacrXqVP", "spotify-LT:track:3KHwhq1ZsfBwRYtacrXqVP", "spotify-LU:track:3KHwhq1ZsfBwRYtacrXqVP", "spotify-LV:track:3KHwhq1ZsfBwRYtacrXqVP", "spotify-MC:track:3KHwhq1ZsfBwRYtacrXqVP", "spotify-MT:track:3KHwhq1ZsfBwRYtacrXqVP", "spotify-MX:track:3KHwhq1ZsfBwRYtacrXqVP", "spotify-MY:track:3KHwhq1ZsfBwRYtacrXqVP", "spotify-NI:track:3KHwhq1ZsfBwRYtacrXqVP", "spotify-NL:track:3KHwhq1ZsfBwRYtacrXqVP", "spotify-NO:track:3KHwhq1ZsfBwRYtacrXqVP", "spotify-NZ:track:3KHwhq1ZsfBwRYtacrXqVP", "spotify-PA:track:3KHwhq1ZsfBwRYtacrXqVP", "spotify-PE:track:3KHwhq1ZsfBwRYtacrXqVP", "spotify-PH:track:3KHwhq1ZsfBwRYtacrXqVP", "spotify-PL:track:3KHwhq1ZsfBwRYtacrXqVP", "spotify-PT:track:3KHwhq1ZsfBwRYtacrXqVP", "spotify-PY:track:3KHwhq1ZsfBwRYtacrXqVP", "spotify-RO:track:3KHwhq1ZsfBwRYtacrXqVP", "spotify-SE:track:3KHwhq1ZsfBwRYtacrXqVP", "spotify-SG:track:3KHwhq1ZsfBwRYtacrXqVP", "spotify-SI:track:3KHwhq1ZsfBwRYtacrXqVP", "spotify-SK:track:3KHwhq1ZsfBwRYtacrXqVP", "spotify-SV:track:3KHwhq1ZsfBwRYtacrXqVP", "spotify-TR:track:3KHwhq1ZsfBwRYtacrXqVP", "spotify-TW:track:3KHwhq1ZsfBwRYtacrXqVP", "spotify-US:track:3KHwhq1ZsfBwRYtacrXqVP", "spotify-UY:track:3KHwhq1ZsfBwRYtacrXqVP", "spotify:track:3KHwhq1ZsfBwRYtacrXqVP"], "title": "Set Me Free", "foreign_release_ids": ["spotify-AD:album:0GJ7jQJRIQNDjz54cPo2XI", "spotify-AR:album:0GJ7jQJRIQNDjz54cPo2XI", "spotify-AT:album:0GJ7jQJRIQNDjz54cPo2XI", "spotify-AU:album:0GJ7jQJRIQNDjz54cPo2XI", "spotify-BE:album:0GJ7jQJRIQNDjz54cPo2XI", "spotify-BG:album:0GJ7jQJRIQNDjz54cPo2XI", "spotify-BO:album:0GJ7jQJRIQNDjz54cPo2XI", "spotify-BR:album:0GJ7jQJRIQNDjz54cPo2XI", "spotify-CA:album:0GJ7jQJRIQNDjz54cPo2XI", "spotify-CH:album:0GJ7jQJRIQNDjz54cPo2XI", "spotify-CL:album:0GJ7jQJRIQNDjz54cPo2XI", "spotify-CO:album:0GJ7jQJRIQNDjz54cPo2XI", "spotify-CR:album:0GJ7jQJRIQNDjz54cPo2XI", "spotify-CY:album:0GJ7jQJRIQNDjz54cPo2XI", "spotify-CZ:album:0GJ7jQJRIQNDjz54cPo2XI", "spotify-DE:album:0GJ7jQJRIQNDjz54cPo2XI", "spotify-DK:album:0GJ7jQJRIQNDjz54cPo2XI", "spotify-DO:album:0GJ7jQJRIQNDjz54cPo2XI", "spotify-EC:album:0GJ7jQJRIQNDjz54cPo2XI", "spotify-EE:album:0GJ7jQJRIQNDjz54cPo2XI", "spotify-ES:album:0GJ7jQJRIQNDjz54cPo2XI", "spotify-FI:album:0GJ7jQJRIQNDjz54cPo2XI", "spotify-FR:album:0GJ7jQJRIQNDjz54cPo2XI", "spotify-GB:album:0GJ7jQJRIQNDjz54cPo2XI", "spotify-GR:album:0GJ7jQJRIQNDjz54cPo2XI", "spotify-GT:album:0GJ7jQJRIQNDjz54cPo2XI", "spotify-HK:album:0GJ7jQJRIQNDjz54cPo2XI", "spotify-HN:album:0GJ7jQJRIQNDjz54cPo2XI", "spotify-HR:album:0GJ7jQJRIQNDjz54cPo2XI", "spotify-HU:album:0GJ7jQJRIQNDjz54cPo2XI", "spotify-IE:album:0GJ7jQJRIQNDjz54cPo2XI", "spotify-IS:album:0GJ7jQJRIQNDjz54cPo2XI", "spotify-IT:album:0GJ7jQJRIQNDjz54cPo2XI", "spotify-LI:album:0GJ7jQJRIQNDjz54cPo2XI", "spotify-LT:album:0GJ7jQJRIQNDjz54cPo2XI", "spotify-LU:album:0GJ7jQJRIQNDjz54cPo2XI", "spotify-LV:album:0GJ7jQJRIQNDjz54cPo2XI", "spotify-MC:album:0GJ7jQJRIQNDjz54cPo2XI", "spotify-MT:album:0GJ7jQJRIQNDjz54cPo2XI", "spotify-MX:album:0GJ7jQJRIQNDjz54cPo2XI", "spotify-MY:album:0GJ7jQJRIQNDjz54cPo2XI", "spotify-NI:album:0GJ7jQJRIQNDjz54cPo2XI", "spotify-NL:album:0GJ7jQJRIQNDjz54cPo2XI", "spotify-NO:album:0GJ7jQJRIQNDjz54cPo2XI", "spotify-NZ:album:0GJ7jQJRIQNDjz54cPo2XI", "spotify-PA:album:0GJ7jQJRIQNDjz54cPo2XI", "spotify-PE:album:0GJ7jQJRIQNDjz54cPo2XI", "spotify-PH:album:0GJ7jQJRIQNDjz54cPo2XI", "spotify-PL:album:0GJ7jQJRIQNDjz54cPo2XI", "spotify-PT:album:0GJ7jQJRIQNDjz54cPo2XI", "spotify-PY:album:0GJ7jQJRIQNDjz54cPo2XI", "spotify-RO:album:0GJ7jQJRIQNDjz54cPo2XI", "spotify-SE:album:0GJ7jQJRIQNDjz54cPo2XI", "spotify-SG:album:0GJ7jQJRIQNDjz54cPo2XI", "spotify-SI:album:0GJ7jQJRIQNDjz54cPo2XI", "spotify-SK:album:0GJ7jQJRIQNDjz54cPo2XI", "spotify-SV:album:0GJ7jQJRIQNDjz54cPo2XI", "spotify-TR:album:0GJ7jQJRIQNDjz54cPo2XI", "spotify-TW:album:0GJ7jQJRIQNDjz54cPo2XI", "spotify-US:album:0GJ7jQJRIQNDjz54cPo2XI", "spotify-UY:album:0GJ7jQJRIQNDjz54cPo2XI", "spotify:album:0GJ7jQJRIQNDjz54cPo2XI"], "foreign_release_id": "spotify:album:0GJ7jQJRIQNDjz54cPo2XI", "catalog": "spotify", "release": "Money Sucks, Friends Rule", "foreign_id": "spotify:track:3KHwhq1ZsfBwRYtacrXqVP", "id": "TRWKIPV14924286ED2", "audio_summary": {"time_signature": 4, "tempo": 128.014, "energy": 0.7180148275772216, "liveness": 0.05067432305117292, "analysis_url": "http://echonest-analysis.s3.amazonaws.com/TR/dcI5CgtfUDdVdHmW4G5wq5xGwhnxFAGd_fcQzZ2TO4ghkolrc5EAtFpIHifhpJPMYYA77XT8RPOzKh1g0%3D/3/full.json?AWSAccessKeyId=AKIAJRDFEY23UEVW42BQ&Expires=1456369143&Signature=D%2B4/ZlUFAYKia4iyZYFHrXLm418%3D", "speechiness": 0.04288893631368368, "mode": 0, "acousticness": 0.00016895866533807015, "danceability": 0.719279972779344, "key": 8, "duration": 247.36, "loudness": -4.443, "valence": 0.5674423179399315, "instrumentalness": 0.39957022935368647}}}}