{"response": {"status": {"version": "4.2", "code": 0, "message": "Success"}, "track": {"status": "complete", "song_id": "SOJJAOR14C0CA2A061", "artist": "Kygo", "foreign_ids": ["spotify-AD:track:4iZPNYqzI2L0uwuUKun7Aa", "spotify-AR:track:4iZPNYqzI2L0uwuUKun7Aa", "spotify-AT:track:4iZPNYqzI2L0uwuUKun7Aa", "spotify-AU:track:4iZPNYqzI2L0uwuUKun7Aa", "spotify-BE:track:4iZPNYqzI2L0uwuUKun7Aa", "spotify-BG:track:4iZPNYqzI2L0uwuUKun7Aa", "spotify-BO:track:4iZPNYqzI2L0uwuUKun7Aa", "spotify-BR:track:4iZPNYqzI2L0uwuUKun7Aa", "spotify-CA:track:4iZPNYqzI2L0uwuUKun7Aa", "spotify-CH:track:4iZPNYqzI2L0uwuUKun7Aa", "spotify-CL:track:4iZPNYqzI2L0uwuUKun7Aa", "spotify-CO:track:4iZPNYqzI2L0uwuUKun7Aa", "spotify-CR:track:4iZPNYqzI2L0uwuUKun7Aa", "spotify-CY:track:4iZPNYqzI2L0uwuUKun7Aa", "spotify-CZ:track:4iZPNYqzI2L0uwuUKun7Aa", "spotify-DE:track:4iZPNYqzI2L0uwuUKun7Aa", "spotify-DK:track:4iZPNYqzI2L0uwuUKun7Aa", "spotify-DO:track:4iZPNYqzI2L0uwuUKun7Aa", "spotify-EC:track:4iZPNYqzI2L0uwuUKun7Aa", "spotify-EE:track:4iZPNYqzI2L0uwuUKun7Aa", "spotify-ES:track:4iZPNYqzI2L0uwuUKun7Aa", "spotify-FI:track:4iZPNYqzI2L0uwuUKun7Aa", "spotify-FR:track:4iZPNYqzI2L0uwuUKun7Aa", "spotify-GB:track:4iZPNYqzI2L0uwuUKun7Aa", "spotify-GR:track:4iZPNYqzI2L0uwuUKun7Aa", "spotify-GT:track:4iZPNYqzI2L0uwuUKun7Aa", "spotify-HK:track:4iZPNYqzI2L0uwuUKun7Aa", "spotify-HN:track:4iZPNYqzI2L0uwuUKun7Aa", "spotify-HR:track:4iZPNYqzI2L0uwuUKun7Aa", "spotify-HU:track:4iZPNYqzI2L0uwuUKun7Aa", "spotify-IE:track:4iZPNYqzI2L0uwuUKun7Aa", "spotify-IS:track:4iZPNYqzI2L0uwuUKun7Aa", "spotify-IT:track:4iZPNYqzI2L0uwuUKun7Aa", "spotify-LI:track:4iZPNYqzI2L0uwuUKun7Aa", "spotify-LT:track:4iZPNYqzI2L0uwuUKun7Aa", "spotify-LU:track:4iZPNYqzI2L0uwuUKun7Aa", "spotify-LV:track:4iZPNYqzI2L0uwuUKun7Aa", "spotify-MC:track:4iZPNYqzI2L0uwuUKun7Aa", "spotify-MT:track:4iZPNYqzI2L0uwuUKun7Aa", "spotify-MX:track:4iZPNYqzI2L0uwuUKun7Aa", "spotify-MY:track:4iZPNYqzI2L0uwuUKun7Aa", "spotify-NI:track:4iZPNYqzI2L0uwuUKun7Aa", "spotify-NL:track:4iZPNYqzI2L0uwuUKun7Aa", "spotify-NO:track:4iZPNYqzI2L0uwuUKun7Aa", "spotify-NZ:track:4iZPNYqzI2L0uwuUKun7Aa", "spotify-PA:track:4iZPNYqzI2L0uwuUKun7Aa", "spotify-PE:track:4iZPNYqzI2L0uwuUKun7Aa", "spotify-PH:track:4iZPNYqzI2L0uwuUKun7Aa", "spotify-PL:track:4iZPNYqzI2L0uwuUKun7Aa", "spotify-PT:track:4iZPNYqzI2L0uwuUKun7Aa", "spotify-PY:track:4iZPNYqzI2L0uwuUKun7Aa", "spotify-RO:track:4iZPNYqzI2L0uwuUKun7Aa", "spotify-SE:track:4iZPNYqzI2L0uwuUKun7Aa", "spotify-SG:track:4iZPNYqzI2L0uwuUKun7Aa", "spotify-SI:track:4iZPNYqzI2L0uwuUKun7Aa", "spotify-SK:track:4iZPNYqzI2L0uwuUKun7Aa", "spotify-SV:track:4iZPNYqzI2L0uwuUKun7Aa", "spotify-TR:track:4iZPNYqzI2L0uwuUKun7Aa", "spotify-TW:track:4iZPNYqzI2L0uwuUKun7Aa", "spotify-US:track:4iZPNYqzI2L0uwuUKun7Aa", "spotify-UY:track:4iZPNYqzI2L0uwuUKun7Aa", "spotify:track:4iZPNYqzI2L0uwuUKun7Aa"], "title": "Stole the Show", "foreign_release_ids": ["spotify-AD:album:26bzHnyTkFBFHUFeRwFDn7", "spotify-AR:album:26bzHnyTkFBFHUFeRwFDn7", "spotify-AT:album:26bzHnyTkFBFHUFeRwFDn7", "spotify-AU:album:26bzHnyTkFBFHUFeRwFDn7", "spotify-BE:album:26bzHnyTkFBFHUFeRwFDn7", "spotify-BG:album:26bzHnyTkFBFHUFeRwFDn7", "spotify-BO:album:26bzHnyTkFBFHUFeRwFDn7", "spotify-BR:album:26bzHnyTkFBFHUFeRwFDn7", "spotify-CA:album:26bzHnyTkFBFHUFeRwFDn7", "spotify-CH:album:26bzHnyTkFBFHUFeRwFDn7", "spotify-CL:album:26bzHnyTkFBFHUFeRwFDn7", "spotify-CO:album:26bzHnyTkFBFHUFeRwFDn7", "spotify-CR:album:26bzHnyTkFBFHUFeRwFDn7", "spotify-CY:album:26bzHnyTkFBFHUFeRwFDn7", "spotify-CZ:album:26bzHnyTkFBFHUFeRwFDn7", "spotify-DE:album:26bzHnyTkFBFHUFeRwFDn7", "spotify-DK:album:26bzHnyTkFBFHUFeRwFDn7", "spotify-DO:album:26bzHnyTkFBFHUFeRwFDn7", "spotify-EC:album:26bzHnyTkFBFHUFeRwFDn7", "spotify-EE:album:26bzHnyTkFBFHUFeRwFDn7", "spotify-ES:album:26bzHnyTkFBFHUFeRwFDn7", "spotify-FI:album:26bzHnyTkFBFHUFeRwFDn7", "spotify-FR:album:26bzHnyTkFBFHUFeRwFDn7", "spotify-GB:album:26bzHnyTkFBFHUFeRwFDn7", "spotify-GR:album:26bzHnyTkFBFHUFeRwFDn7", "spotify-GT:album:26bzHnyTkFBFHUFeRwFDn7", "spotify-HK:album:26bzHnyTkFBFHUFeRwFDn7", "spotify-HN:album:26bzHnyTkFBFHUFeRwFDn7", "spotify-HR:album:26bzHnyTkFBFHUFeRwFDn7", "spotify-HU:album:26bzHnyTkFBFHUFeRwFDn7", "spotify-IE:album:26bzHnyTkFBFHUFeRwFDn7", "spotify-IS:album:26bzHnyTkFBFHUFeRwFDn7", "spotify-IT:album:26bzHnyTkFBFHUFeRwFDn7", "spotify-LI:album:26bzHnyTkFBFHUFeRwFDn7", "spotify-LT:album:26bzHnyTkFBFHUFeRwFDn7", "spotify-LU:album:26bzHnyTkFBFHUFeRwFDn7", "spotify-LV:album:26bzHnyTkFBFHUFeRwFDn7", "spotify-MC:album:26bzHnyTkFBFHUFeRwFDn7", "spotify-MT:album:26bzHnyTkFBFHUFeRwFDn7", "spotify-MX:album:26bzHnyTkFBFHUFeRwFDn7", "spotify-MY:album:26bzHnyTkFBFHUFeRwFDn7", "spotify-NI:album:26bzHnyTkFBFHUFeRwFDn7", "spotify-NL:album:26bzHnyTkFBFHUFeRwFDn7", "spotify-NO:album:26bzHnyTkFBFHUFeRwFDn7", "spotify-NZ:album:26bzHnyTkFBFHUFeRwFDn7", "spotify-PA:album:26bzHnyTkFBFHUFeRwFDn7", "spotify-PE:album:26bzHnyTkFBFHUFeRwFDn7", "spotify-PH:album:26bzHnyTkFBFHUFeRwFDn7", "spotify-PL:album:26bzHnyTkFBFHUFeRwFDn7", "spotify-PT:album:26bzHnyTkFBFHUFeRwFDn7", "spotify-PY:album:26bzHnyTkFBFHUFeRwFDn7", "spotify-RO:album:26bzHnyTkFBFHUFeRwFDn7", "spotify-SE:album:26bzHnyTkFBFHUFeRwFDn7", "spotify-SG:album:26bzHnyTkFBFHUFeRwFDn7", "spotify-SI:album:26bzHnyTkFBFHUFeRwFDn7", "spotify-SK:album:26bzHnyTkFBFHUFeRwFDn7", "spotify-SV:album:26bzHnyTkFBFHUFeRwFDn7", "spotify-TR:album:26bzHnyTkFBFHUFeRwFDn7", "spotify-TW:album:26bzHnyTkFBFHUFeRwFDn7", "spotify-US:album:26bzHnyTkFBFHUFeRwFDn7", "spotify-UY:album:26bzHnyTkFBFHUFeRwFDn7", "spotify:album:26bzHnyTkFBFHUFeRwFDn7"], "foreign_release_id": "spotify:album:26bzHnyTkFBFHUFeRwFDn7", "catalog": "spotify", "release": "Stole the Show", "foreign_id": "spotify:track:4iZPNYqzI2L0uwuUKun7Aa", "id": "TRKCMUI14C03492870", "audio_summary": {"time_signature": 4, "tempo": 99.879, "energy": 0.6619842132401925, "liveness": 0.15170647691212266, "analysis_url": "http://echonest-analysis.s3.amazonaws.com/TR/3SHy5w6bFqPotUxbKwi1fAdrfbqGT9ULdFj-r_A9kjp96AKbCOVut4mn9kpFGQouclKwkrVX3eD9Q7GpA%3D/3/full.json?AWSAccessKeyId=AKIAJRDFEY23UEVW42BQ&Expires=1456355584&Signature=Q3snZZHpC2yNfWE3uSHgCygvh%2Bw%3D", "speechiness": 0.174372293061906, "mode": 0, "acousticness": 0.15461350880729346, "danceability": 0.6785114558899242, "key": 8, "duration": 222.80136, "loudness": -6.069, "valence": 0.43420152994348266, "instrumentalness": 7.195295720233342e-07}}}}