{"response": {"status": {"version": "4.2", "code": 0, "message": "Success"}, "track": {"status": "complete", "song_id": "SOJVNCB14875B13F0F", "artist": "Perfume Genius", "foreign_ids": ["spotify-AD:track:4N9gagQ5IfgSVSBFQKKa66", "spotify-AR:track:4N9gagQ5IfgSVSBFQKKa66", "spotify-AT:track:4N9gagQ5IfgSVSBFQKKa66", "spotify-AU:track:4N9gagQ5IfgSVSBFQKKa66", "spotify-BE:track:4N9gagQ5IfgSVSBFQKKa66", "spotify-BG:track:4N9gagQ5IfgSVSBFQKKa66", "spotify-BO:track:4N9gagQ5IfgSVSBFQKKa66", "spotify-BR:track:4N9gagQ5IfgSVSBFQKKa66", "spotify-CA:track:4N9gagQ5IfgSVSBFQKKa66", "spotify-CH:track:4N9gagQ5IfgSVSBFQKKa66", "spotify-CL:track:4N9gagQ5IfgSVSBFQKKa66", "spotify-CO:track:4N9gagQ5IfgSVSBFQKKa66", "spotify-CR:track:4N9gagQ5IfgSVSBFQKKa66", "spotify-CY:track:4N9gagQ5IfgSVSBFQKKa66", "spotify-CZ:track:4N9gagQ5IfgSVSBFQKKa66", "spotify-DE:track:4N9gagQ5IfgSVSBFQKKa66", "spotify-DK:track:4N9gagQ5IfgSVSBFQKKa66", "spotify-DO:track:4N9gagQ5IfgSVSBFQKKa66", "spotify-EC:track:4N9gagQ5IfgSVSBFQKKa66", "spotify-EE:track:4N9gagQ5IfgSVSBFQKKa66", "spotify-ES:track:4N9gagQ5IfgSVSBFQKKa66", "spotify-FI:track:4N9gagQ5IfgSVSBFQKKa66", "spotify-FR:track:4N9gagQ5IfgSVSBFQKKa66", "spotify-GR:track:4N9gagQ5IfgSVSBFQKKa66", "spotify-GT:track:4N9gagQ5IfgSVSBFQKKa66", "spotify-HK:track:4N9gagQ5IfgSVSBFQKKa66", "spotify-HN:track:4N9gagQ5IfgSVSBFQKKa66", "spotify-HR:track:4N9gagQ5IfgSVSBFQKKa66", "spotify-HU:track:4N9gagQ5IfgSVSBFQKKa66", "spotify-IS:track:4N9gagQ5IfgSVSBFQKKa66", "spotify-IT:track:4N9gagQ5IfgSVSBFQKKa66", "spotify-LI:track:4N9gagQ5IfgSVSBFQKKa66", "spotify-LT:track:4N9gagQ5IfgSVSBFQKKa66", "spotify-LU:track:4N9gagQ5IfgSVSBFQKKa66", "spotify-LV:track:4N9gagQ5IfgSVSBFQKKa66", "spotify-MC:track:4N9gagQ5IfgSVSBFQKKa66", "spotify-MT:track:4N9gagQ5IfgSVSBFQKKa66", "spotify-MX:track:4N9gagQ5IfgSVSBFQKKa66", "spotify-MY:track:4N9gagQ5IfgSVSBFQKKa66", "spotify-NI:track:4N9gagQ5IfgSVSBFQKKa66", "spotify-NL:track:4N9gagQ5IfgSVSBFQKKa66", "spotify-NO:track:4N9gagQ5IfgSVSBFQKKa66", "spotify-NZ:track:4N9gagQ5IfgSVSBFQKKa66", "spotify-PA:track:4N9gagQ5IfgSVSBFQKKa66", "spotify-PE:track:4N9gagQ5IfgSVSBFQKKa66", "spotify-PH:track:4N9gagQ5IfgSVSBFQKKa66", "spotify-PL:track:4N9gagQ5IfgSVSBFQKKa66", "spotify-PT:track:4N9gagQ5IfgSVSBFQKKa66", "spotify-PY:track:4N9gagQ5IfgSVSBFQKKa66", "spotify-RO:track:4N9gagQ5IfgSVSBFQKKa66", "spotify-SE:track:4N9gagQ5IfgSVSBFQKKa66", "spotify-SG:track:4N9gagQ5IfgSVSBFQKKa66", "spotify-SI:track:4N9gagQ5IfgSVSBFQKKa66", "spotify-SK:track:4N9gagQ5IfgSVSBFQKKa66", "spotify-SV:track:4N9gagQ5IfgSVSBFQKKa66", "spotify-TR:track:4N9gagQ5IfgSVSBFQKKa66", "spotify-TW:track:4N9gagQ5IfgSVSBFQKKa66", "spotify-US:track:4N9gagQ5IfgSVSBFQKKa66", "spotify-UY:track:4N9gagQ5IfgSVSBFQKKa66", "spotify:track:4N9gagQ5IfgSVSBFQKKa66"], "title": "I'm a Mother", "foreign_release_ids": ["spotify-AD:album:28FxHb9OJRzAch4DwUUsaT", "spotify-AR:album:28FxHb9OJRzAch4DwUUsaT", "spotify-AT:album:28FxHb9OJRzAch4DwUUsaT", "spotify-AU:album:28FxHb9OJRzAch4DwUUsaT", "spotify-BE:album:28FxHb9OJRzAch4DwUUsaT", "spotify-BG:album:28FxHb9OJRzAch4DwUUsaT", "spotify-BO:album:28FxHb9OJRzAch4DwUUsaT", "spotify-BR:album:28FxHb9OJRzAch4DwUUsaT", "spotify-CA:album:28FxHb9OJRzAch4DwUUsaT", "spotify-CH:album:28FxHb9OJRzAch4DwUUsaT", "spotify-CL:album:28FxHb9OJRzAch4DwUUsaT", "spotify-CO:album:28FxHb9OJRzAch4DwUUsaT", "spotify-CR:album:28FxHb9OJRzAch4DwUUsaT", "spotify-CY:album:28FxHb9OJRzAch4DwUUsaT", "spotify-CZ:album:28FxHb9OJRzAch4DwUUsaT", "spotify-DE:album:28FxHb9OJRzAch4DwUUsaT", "spotify-DK:album:28FxHb9OJRzAch4DwUUsaT", "spotify-DO:album:28FxHb9OJRzAch4DwUUsaT", "spotify-EC:album:28FxHb9OJRzAch4DwUUsaT", "spotify-EE:album:28FxHb9OJRzAch4DwUUsaT", "spotify-ES:album:28FxHb9OJRzAch4DwUUsaT", "spotify-FI:album:28FxHb9OJRzAch4DwUUsaT", "spotify-FR:album:28FxHb9OJRzAch4DwUUsaT", "spotify-GR:album:28FxHb9OJRzAch4DwUUsaT", "spotify-GT:album:28FxHb9OJRzAch4DwUUsaT", "spotify-HK:album:28FxHb9OJRzAch4DwUUsaT", "spotify-HN:album:28FxHb9OJRzAch4DwUUsaT", "spotify-HR:album:28FxHb9OJRzAch4DwUUsaT", "spotify-HU:album:28FxHb9OJRzAch4DwUUsaT", "spotify-IS:album:28FxHb9OJRzAch4DwUUsaT", "spotify-IT:album:28FxHb9OJRzAch4DwUUsaT", "spotify-LI:album:28FxHb9OJRzAch4DwUUsaT", "spotify-LT:album:28FxHb9OJRzAch4DwUUsaT", "spotify-LU:album:28FxHb9OJRzAch4DwUUsaT", "spotify-LV:album:28FxHb9OJRzAch4DwUUsaT", "spotify-MC:album:28FxHb9OJRzAch4DwUUsaT", "spotify-MT:album:28FxHb9OJRzAch4DwUUsaT", "spotify-MX:album:28FxHb9OJRzAch4DwUUsaT", "spotify-MY:album:28FxHb9OJRzAch4DwUUsaT", "spotify-NI:album:28FxHb9OJRzAch4DwUUsaT", "spotify-NL:album:28FxHb9OJRzAch4DwUUsaT", "spotify-NO:album:28FxHb9OJRzAch4DwUUsaT", "spotify-NZ:album:28FxHb9OJRzAch4DwUUsaT", "spotify-PA:album:28FxHb9OJRzAch4DwUUsaT", "spotify-PE:album:28FxHb9OJRzAch4DwUUsaT", "spotify-PH:album:28FxHb9OJRzAch4DwUUsaT", "spotify-PL:album:28FxHb9OJRzAch4DwUUsaT", "spotify-PT:album:28FxHb9OJRzAch4DwUUsaT", "spotify-PY:album:28FxHb9OJRzAch4DwUUsaT", "spotify-RO:album:28FxHb9OJRzAch4DwUUsaT", "spotify-SE:album:28FxHb9OJRzAch4DwUUsaT", "spotify-SG:album:28FxHb9OJRzAch4DwUUsaT", "spotify-SI:album:28FxHb9OJRzAch4DwUUsaT", "spotify-SK:album:28FxHb9OJRzAch4DwUUsaT", "spotify-SV:album:28FxHb9OJRzAch4DwUUsaT", "spotify-TR:album:28FxHb9OJRzAch4DwUUsaT", "spotify-TW:album:28FxHb9OJRzAch4DwUUsaT", "spotify-US:album:28FxHb9OJRzAch4DwUUsaT", "spotify-UY:album:28FxHb9OJRzAch4DwUUsaT", "spotify:album:28FxHb9OJRzAch4DwUUsaT"], "foreign_release_id": "spotify:album:28FxHb9OJRzAch4DwUUsaT", "catalog": "spotify", "release": "Too Bright", "foreign_id": "spotify:track:4N9gagQ5IfgSVSBFQKKa66", "id": "TRVJGBX14869FB411F", "audio_summary": {"time_signature": 3, "tempo": 118.451, "energy": 0.14237047547158, "liveness": 0.11168971697272867, "analysis_url": "http://echonest-analysis.s3.amazonaws.com/TR/YSDC0A0cp2K3Rv5hRPctrmnpON2vwNWX_0y2LP6Cg6WRo-Gsh6nW_qJ0ni4a9BvqMqS8kXTnEmrGLexE8%3D/3/full.json?AWSAccessKeyId=AKIAJRDFEY23UEVW42BQ&Expires=1456378954&Signature=Bv%2BETP2GlvtaXc4LUGyHK9pY6go%3D", "speechiness": 0.03863238838986649, "mode": 0, "acousticness": 0.9660717965257519, "danceability": 0.2934791764494774, "key": 11, "duration": 210.57333, "loudness": -17.647, "valence": 0.07537652605336613, "instrumentalness": 0.8987216364927568}}}}