{"response": {"status": {"version": "4.2", "code": 0, "message": "Success"}, "track": {"status": "complete", "song_id": "SOJHERN1360E459999", "artist": "SBTRKT", "foreign_ids": ["spotify-AD:track:4YieaHATpFhQOTRbEAOXGp", "spotify-AR:track:4YieaHATpFhQOTRbEAOXGp", "spotify-AT:track:4YieaHATpFhQOTRbEAOXGp", "spotify-AU:track:4YieaHATpFhQOTRbEAOXGp", "spotify-BE:track:4YieaHATpFhQOTRbEAOXGp", "spotify-BG:track:4YieaHATpFhQOTRbEAOXGp", "spotify-BO:track:4YieaHATpFhQOTRbEAOXGp", "spotify-BR:track:4YieaHATpFhQOTRbEAOXGp", "spotify-CA:track:4YieaHATpFhQOTRbEAOXGp", "spotify-CH:track:4YieaHATpFhQOTRbEAOXGp", "spotify-CL:track:4YieaHATpFhQOTRbEAOXGp", "spotify-CO:track:4YieaHATpFhQOTRbEAOXGp", "spotify-CR:track:4YieaHATpFhQOTRbEAOXGp", "spotify-CY:track:4YieaHATpFhQOTRbEAOXGp", "spotify-CZ:track:4YieaHATpFhQOTRbEAOXGp", "spotify-DE:track:4YieaHATpFhQOTRbEAOXGp", "spotify-DK:track:4YieaHATpFhQOTRbEAOXGp", "spotify-DO:track:4YieaHATpFhQOTRbEAOXGp", "spotify-EC:track:4YieaHATpFhQOTRbEAOXGp", "spotify-EE:track:4YieaHATpFhQOTRbEAOXGp", "spotify-ES:track:4YieaHATpFhQOTRbEAOXGp", "spotify-FI:track:4YieaHATpFhQOTRbEAOXGp", "spotify-FR:track:4YieaHATpFhQOTRbEAOXGp", "spotify-GB:track:4YieaHATpFhQOTRbEAOXGp", "spotify-GR:track:4YieaHATpFhQOTRbEAOXGp", "spotify-GT:track:4YieaHATpFhQOTRbEAOXGp", "spotify-HK:track:4YieaHATpFhQOTRbEAOXGp", "spotify-HN:track:4YieaHATpFhQOTRbEAOXGp", "spotify-HR:track:4YieaHATpFhQOTRbEAOXGp", "spotify-HU:track:4YieaHATpFhQOTRbEAOXGp", "spotify-IE:track:4YieaHATpFhQOTRbEAOXGp", "spotify-IS:track:4YieaHATpFhQOTRbEAOXGp", "spotify-IT:track:4YieaHATpFhQOTRbEAOXGp", "spotify-LI:track:4YieaHATpFhQOTRbEAOXGp", "spotify-LT:track:4YieaHATpFhQOTRbEAOXGp", "spotify-LU:track:4YieaHATpFhQOTRbEAOXGp", "spotify-LV:track:4YieaHATpFhQOTRbEAOXGp", "spotify-MC:track:4YieaHATpFhQOTRbEAOXGp", "spotify-MT:track:4YieaHATpFhQOTRbEAOXGp", "spotify-MX:track:4YieaHATpFhQOTRbEAOXGp", "spotify-MY:track:4YieaHATpFhQOTRbEAOXGp", "spotify-NI:track:4YieaHATpFhQOTRbEAOXGp", "spotify-NL:track:4YieaHATpFhQOTRbEAOXGp", "spotify-NO:track:4YieaHATpFhQOTRbEAOXGp", "spotify-NZ:track:4YieaHATpFhQOTRbEAOXGp", "spotify-PA:track:4YieaHATpFhQOTRbEAOXGp", "spotify-PE:track:4YieaHATpFhQOTRbEAOXGp", "spotify-PH:track:4YieaHATpFhQOTRbEAOXGp", "spotify-PL:track:4YieaHATpFhQOTRbEAOXGp", "spotify-PT:track:4YieaHATpFhQOTRbEAOXGp", "spotify-PY:track:4YieaHATpFhQOTRbEAOXGp", "spotify-RO:track:4YieaHATpFhQOTRbEAOXGp", "spotify-SE:track:4YieaHATpFhQOTRbEAOXGp", "spotify-SG:track:4YieaHATpFhQOTRbEAOXGp", "spotify-SI:track:4YieaHATpFhQOTRbEAOXGp", "spotify-SK:track:4YieaHATpFhQOTRbEAOXGp", "spotify-SV:track:4YieaHATpFhQOTRbEAOXGp", "spotify-TR:track:4YieaHATpFhQOTRbEAOXGp", "spotify-TW:track:4YieaHATpFhQOTRbEAOXGp", "spotify-US:track:4YieaHATpFhQOTRbEAOXGp", "spotify-UY:track:4YieaHATpFhQOTRbEAOXGp", "spotify:track:4YieaHATpFhQOTRbEAOXGp"], "title": "Go Bang", "foreign_release_ids": ["spotify-AD:album:5fP2kgfePJZF4nB1XqC1i8", "spotify-AR:album:5fP2kgfePJZF4nB1XqC1i8", "spotify-AT:album:5fP2kgfePJZF4nB1XqC1i8", "spotify-AU:album:5fP2kgfePJZF4nB1XqC1i8", "spotify-BE:album:5fP2kgfePJZF4nB1XqC1i8", "spotify-BG:album:5fP2kgfePJZF4nB1XqC1i8", "spotify-BO:album:5fP2kgfePJZF4nB1XqC1i8", "spotify-BR:album:5fP2kgfePJZF4nB1XqC1i8", "spotify-CA:album:5fP2kgfePJZF4nB1XqC1i8", "spotify-CH:album:5fP2kgfePJZF4nB1XqC1i8", "spotify-CL:album:5fP2kgfePJZF4nB1XqC1i8", "spotify-CO:album:5fP2kgfePJZF4nB1XqC1i8", "spotify-CR:album:5fP2kgfePJZF4nB1XqC1i8", "spotify-CY:album:5fP2kgfePJZF4nB1XqC1i8", "spotify-CZ:album:5fP2kgfePJZF4nB1XqC1i8", "spotify-DE:album:5fP2kgfePJZF4nB1XqC1i8", "spotify-DK:album:5fP2kgfePJZF4nB1XqC1i8", "spotify-DO:album:5fP2kgfePJZF4nB1XqC1i8", "spotify-EC:album:5fP2kgfePJZF4nB1XqC1i8", "spotify-EE:album:5fP2kgfePJZF4nB1XqC1i8", "spotify-ES:album:5fP2kgfePJZF4nB1XqC1i8", "spotify-FI:album:5fP2kgfePJZF4nB1XqC1i8", "spotify-FR:album:5fP2kgfePJZF4nB1XqC1i8", "spotify-GB:album:5fP2kgfePJZF4nB1XqC1i8", "spotify-GR:album:5fP2kgfePJZF4nB1XqC1i8", "spotify-GT:album:5fP2kgfePJZF4nB1XqC1i8", "spotify-HK:album:5fP2kgfePJZF4nB1XqC1i8", "spotify-HN:album:5fP2kgfePJZF4nB1XqC1i8", "spotify-HR:album:5fP2kgfePJZF4nB1XqC1i8", "spotify-HU:album:5fP2kgfePJZF4nB1XqC1i8", "spotify-IE:album:5fP2kgfePJZF4nB1XqC1i8", "spotify-IS:album:5fP2kgfePJZF4nB1XqC1i8", "spotify-IT:album:5fP2kgfePJZF4nB1XqC1i8", "spotify-LI:album:5fP2kgfePJZF4nB1XqC1i8", "spotify-LT:album:5fP2kgfePJZF4nB1XqC1i8", "spotify-LU:album:5fP2kgfePJZF4nB1XqC1i8", "spotify-LV:album:5fP2kgfePJZF4nB1XqC1i8", "spotify-MC:album:5fP2kgfePJZF4nB1XqC1i8", "spotify-MT:album:5fP2kgfePJZF4nB1XqC1i8", "spotify-MX:album:5fP2kgfePJZF4nB1XqC1i8", "spotify-MY:album:5fP2kgfePJZF4nB1XqC1i8", "spotify-NI:album:5fP2kgfePJZF4nB1XqC1i8", "spotify-NL:album:5fP2kgfePJZF4nB1XqC1i8", "spotify-NO:album:5fP2kgfePJZF4nB1XqC1i8", "spotify-NZ:album:5fP2kgfePJZF4nB1XqC1i8", "spotify-PA:album:5fP2kgfePJZF4nB1XqC1i8", "spotify-PE:album:5fP2kgfePJZF4nB1XqC1i8", "spotify-PH:album:5fP2kgfePJZF4nB1XqC1i8", "spotify-PL:album:5fP2kgfePJZF4nB1XqC1i8", "spotify-PT:album:5fP2kgfePJZF4nB1XqC1i8", "spotify-PY:album:5fP2kgfePJZF4nB1XqC1i8", "spotify-RO:album:5fP2kgfePJZF4nB1XqC1i8", "spotify-SE:album:5fP2kgfePJZF4nB1XqC1i8", "spotify-SG:album:5fP2kgfePJZF4nB1XqC1i8", "spotify-SI:album:5fP2kgfePJZF4nB1XqC1i8", "spotify-SK:album:5fP2kgfePJZF4nB1XqC1i8", "spotify-SV:album:5fP2kgfePJZF4nB1XqC1i8", "spotify-TR:album:5fP2kgfePJZF4nB1XqC1i8", "spotify-TW:album:5fP2kgfePJZF4nB1XqC1i8", "spotify-US:album:5fP2kgfePJZF4nB1XqC1i8", "spotify-UY:album:5fP2kgfePJZF4nB1XqC1i8", "spotify:album:5fP2kgfePJZF4nB1XqC1i8"], "foreign_release_id": "spotify:album:5fP2kgfePJZF4nB1XqC1i8", "catalog": "spotify", "release": "SBTRKT", "foreign_id": "spotify:track:4YieaHATpFhQOTRbEAOXGp", "id": "TRRPBEE144D155FED9", "audio_summary": {"time_signature": 4, "tempo": 134.014, "energy": 0.5589991826806769, "liveness": 0.11240541427190404, "analysis_url": "http://echonest-analysis.s3.amazonaws.com/TR/4d8NRgu3g-4SvQ8tqQLV4FT-9r-KlolexHu6yE3s2kciC5awTELpt6A7OJ0pDr2bwgD7ty6WII5d6U6_8%3D/3/full.json?AWSAccessKeyId=AKIAJRDFEY23UEVW42BQ&Expires=1456361783&Signature=GBwR7gmwl/XtuJ/VNBQzgYRss94%3D", "speechiness": 0.06458710305978438, "mode": 1, "acousticness": 0.010740955112704042, "danceability": 0.7054850777323192, "key": 0, "duration": 211.8, "loudness": -11.197, "valence": 0.34842757436055166, "instrumentalness": 0.7796191245755435}}}}