{"response": {"status": {"version": "4.2", "code": 0, "message": "Success"}, "track": {"status": "complete", "song_id": "SOPDWQY1366A0A75B9", "artist": "Ben Folds Five", "foreign_ids": ["spotify-AD:track:6rPT8tCXKwJXuwxTL5d6om", "spotify-AR:track:6rPT8tCXKwJXuwxTL5d6om", "spotify-AT:track:6rPT8tCXKwJXuwxTL5d6om", "spotify-BE:track:6rPT8tCXKwJXuwxTL5d6om", "spotify-BG:track:6rPT8tCXKwJXuwxTL5d6om", "spotify-BO:track:6rPT8tCXKwJXuwxTL5d6om", "spotify-BR:track:6rPT8tCXKwJXuwxTL5d6om", "spotify-CA:track:6rPT8tCXKwJXuwxTL5d6om", "spotify-CH:track:6rPT8tCXKwJXuwxTL5d6om", "spotify-CL:track:6rPT8tCXKwJXuwxTL5d6om", "spotify-CO:track:6rPT8tCXKwJXuwxTL5d6om", "spotify-CR:track:6rPT8tCXKwJXuwxTL5d6om", "spotify-CY:track:6rPT8tCXKwJXuwxTL5d6om", "spotify-CZ:track:6rPT8tCXKwJXuwxTL5d6om", "spotify-DE:track:6rPT8tCXKwJXuwxTL5d6om", "spotify-DK:track:6rPT8tCXKwJXuwxTL5d6om", "spotify-DO:track:6rPT8tCXKwJXuwxTL5d6om", "spotify-EC:track:6rPT8tCXKwJXuwxTL5d6om", "spotify-EE:track:6rPT8tCXKwJXuwxTL5d6om", "spotify-ES:track:6rPT8tCXKwJXuwxTL5d6om", "spotify-FI:track:6rPT8tCXKwJXuwxTL5d6om", "spotify-FR:track:6rPT8tCXKwJXuwxTL5d6om", "spotify-GB:track:6rPT8tCXKwJXuwxTL5d6om", "spotify-GR:track:6rPT8tCXKwJXuwxTL5d6om", "spotify-GT:track:6rPT8tCXKwJXuwxTL5d6om", "spotify-HK:track:6rPT8tCXKwJXuwxTL5d6om", "spotify-HN:track:6rPT8tCXKwJXuwxTL5d6om", "spotify-HR:track:6rPT8tCXKwJXuwxTL5d6om", "spotify-HU:track:6rPT8tCXKwJXuwxTL5d6om", "spotify-IE:track:6rPT8tCXKwJXuwxTL5d6om", "spotify-IS:track:6rPT8tCXKwJXuwxTL5d6om", "spotify-IT:track:6rPT8tCXKwJXuwxTL5d6om", "spotify-LI:track:6rPT8tCXKwJXuwxTL5d6om", "spotify-LT:track:6rPT8tCXKwJXuwxTL5d6om", "spotify-LU:track:6rPT8tCXKwJXuwxTL5d6om", "spotify-LV:track:6rPT8tCXKwJXuwxTL5d6om", "spotify-MC:track:6rPT8tCXKwJXuwxTL5d6om", "spotify-MT:track:6rPT8tCXKwJXuwxTL5d6om", "spotify-MX:track:6rPT8tCXKwJXuwxTL5d6om", "spotify-MY:track:6rPT8tCXKwJXuwxTL5d6om", "spotify-NI:track:6rPT8tCXKwJXuwxTL5d6om", "spotify-NL:track:6rPT8tCXKwJXuwxTL5d6om", "spotify-NO:track:6rPT8tCXKwJXuwxTL5d6om", "spotify-PA:track:6rPT8tCXKwJXuwxTL5d6om", "spotify-PE:track:6rPT8tCXKwJXuwxTL5d6om", "spotify-PH:track:6rPT8tCXKwJXuwxTL5d6om", "spotify-PL:track:6rPT8tCXKwJXuwxTL5d6om", "spotify-PT:track:6rPT8tCXKwJXuwxTL5d6om", "spotify-PY:track:6rPT8tCXKwJXuwxTL5d6om", "spotify-RO:track:6rPT8tCXKwJXuwxTL5d6om", "spotify-SE:track:6rPT8tCXKwJXuwxTL5d6om", "spotify-SG:track:6rPT8tCXKwJXuwxTL5d6om", "spotify-SI:track:6rPT8tCXKwJXuwxTL5d6om", "spotify-SK:track:6rPT8tCXKwJXuwxTL5d6om", "spotify-SV:track:6rPT8tCXKwJXuwxTL5d6om", "spotify-TR:track:6rPT8tCXKwJXuwxTL5d6om", "spotify-TW:track:6rPT8tCXKwJXuwxTL5d6om", "spotify-US:track:6rPT8tCXKwJXuwxTL5d6om", "spotify-UY:track:6rPT8tCXKwJXuwxTL5d6om", "spotify:track:6rPT8tCXKwJXuwxTL5d6om"], "title": "Tell Me What I Did", "foreign_release_ids": ["spotify-AD:album:1h4LqT4SV5pTlyW6eonP4S", "spotify-AR:album:1h4LqT4SV5pTlyW6eonP4S", "spotify-AT:album:1h4LqT4SV5pTlyW6eonP4S", "spotify-BE:album:1h4LqT4SV5pTlyW6eonP4S", "spotify-BG:album:1h4LqT4SV5pTlyW6eonP4S", "spotify-BO:album:1h4LqT4SV5pTlyW6eonP4S", "spotify-BR:album:1h4LqT4SV5pTlyW6eonP4S", "spotify-CA:album:1h4LqT4SV5pTlyW6eonP4S", "spotify-CH:album:1h4LqT4SV5pTlyW6eonP4S", "spotify-CL:album:1h4LqT4SV5pTlyW6eonP4S", "spotify-CO:album:1h4LqT4SV5pTlyW6eonP4S", "spotify-CR:album:1h4LqT4SV5pTlyW6eonP4S", "spotify-CY:album:1h4LqT4SV5pTlyW6eonP4S", "spotify-CZ:album:1h4LqT4SV5pTlyW6eonP4S", "spotify-DE:album:1h4LqT4SV5pTlyW6eonP4S", "spotify-DK:album:1h4LqT4SV5pTlyW6eonP4S", "spotify-DO:album:1h4LqT4SV5pTlyW6eonP4S", "spotify-EC:album:1h4LqT4SV5pTlyW6eonP4S", "spotify-EE:album:1h4LqT4SV5pTlyW6eonP4S", "spotify-ES:album:1h4LqT4SV5pTlyW6eonP4S", "spotify-FI:album:1h4LqT4SV5pTlyW6eonP4S", "spotify-FR:album:1h4LqT4SV5pTlyW6eonP4S", "spotify-GB:album:1h4LqT4SV5pTlyW6eonP4S", "spotify-GR:album:1h4LqT4SV5pTlyW6eonP4S", "spotify-GT:album:1h4LqT4SV5pTlyW6eonP4S", "spotify-HK:album:1h4LqT4SV5pTlyW6eonP4S", "spotify-HN:album:1h4LqT4SV5pTlyW6eonP4S", "spotify-HR:album:1h4LqT4SV5pTlyW6eonP4S", "spotify-HU:album:1h4LqT4SV5pTlyW6eonP4S", "spotify-IE:album:1h4LqT4SV5pTlyW6eonP4S", "spotify-IS:album:1h4LqT4SV5pTlyW6eonP4S", "spotify-IT:album:1h4LqT4SV5pTlyW6eonP4S", "spotify-LI:album:1h4LqT4SV5pTlyW6eonP4S", "spotify-LT:album:1h4LqT4SV5pTlyW6eonP4S", "spotify-LU:album:1h4LqT4SV5pTlyW6eonP4S", "spotify-LV:album:1h4LqT4SV5pTlyW6eonP4S", "spotify-MC:album:1h4LqT4SV5pTlyW6eonP4S", "spotify-MT:album:1h4LqT4SV5pTlyW6eonP4S", "spotify-MX:album:1h4LqT4SV5pTlyW6eonP4S", "spotify-MY:album:1h4LqT4SV5pTlyW6eonP4S", "spotify-NI:album:1h4LqT4SV5pTlyW6eonP4S", "spotify-NL:album:1h4LqT4SV5pTlyW6eonP4S", "spotify-NO:album:1h4LqT4SV5pTlyW6eonP4S", "spotify-PA:album:1h4LqT4SV5pTlyW6eonP4S", "spotify-PE:album:1h4LqT4SV5pTlyW6eonP4S", "spotify-PH:album:1h4LqT4SV5pTlyW6eonP4S", "spotify-PL:album:1h4LqT4SV5pTlyW6eonP4S", "spotify-PT:album:1h4LqT4SV5pTlyW6eonP4S", "spotify-PY:album:1h4LqT4SV5pTlyW6eonP4S", "spotify-RO:album:1h4LqT4SV5pTlyW6eonP4S", "spotify-SE:album:1h4LqT4SV5pTlyW6eonP4S", "spotify-SG:album:1h4LqT4SV5pTlyW6eonP4S", "spotify-SI:album:1h4LqT4SV5pTlyW6eonP4S", "spotify-SK:album:1h4LqT4SV5pTlyW6eonP4S", "spotify-SV:album:1h4LqT4SV5pTlyW6eonP4S", "spotify-TR:album:1h4LqT4SV5pTlyW6eonP4S", "spotify-TW:album:1h4LqT4SV5pTlyW6eonP4S", "spotify-US:album:1h4LqT4SV5pTlyW6eonP4S", "spotify-UY:album:1h4LqT4SV5pTlyW6eonP4S", "spotify:album:1h4LqT4SV5pTlyW6eonP4S"], "foreign_release_id": "spotify:album:1h4LqT4SV5pTlyW6eonP4S", "catalog": "spotify", "release": "The Best Imitation Of Myself: A Retrospective", "foreign_id": "spotify:track:6rPT8tCXKwJXuwxTL5d6om", "id": "TROZMLN144D1C13C52", "audio_summary": {"time_signature": 4, "tempo": 132.438, "energy": 0.8668893573692069, "liveness": 0.45498432534361966, "analysis_url": "http://echonest-analysis.s3.amazonaws.com/TR/dFr5QAG5Q2WlbzKMiWDG5KHRaix_FAP8uRS0IDasNjIc8pkZ4YtEJeTLmkvkI0i4MbjSOrg0r-ddOFluU%3D/3/full.json?AWSAccessKeyId=AKIAJRDFEY23UEVW42BQ&Expires=1456362261&Signature=90pWOI0HE6FdstclClhVNAn9W7U%3D", "speechiness": 0.05513276323194283, "mode": 0, "acousticness": 0.013554385114446047, "danceability": 0.38586692506301473, "key": 11, "duration": 169.04, "loudness": -5.469, "valence": 0.5392916103637619, "instrumentalness": 2.594808863438189e-07}}}}